{
  "seo_title": "Jobs & Karriere, feelMOOR Gesundresort",
  "seo_description": "Offene Stellen und Karrieremöglichkeiten im feelMOOR Gesundresort Bad Wurzach. Werde Teil unseres Teams.",
  "hero_caption": "Karriere",
  "hero_heading": "Jobs & Karriere",
  "hero_intro": "Werden Sie Teil des feelMOOR-Teams, arbeiten wo andere Urlaub machen.",
  "intro_heading": "Arbeiten im feelMOOR",
  "intro_body": "Das feelMOOR Gesundresort Bad Wurzach ist ein wachsendes Unternehmen mit einem engagierten Team. Wir suchen Menschen, die Freude am Umgang mit Gästen haben, Gesundheit und Wohlbefinden schätzen und in einer der schönsten Regionen Deutschlands arbeiten möchten.",
  "no_open_positions_note": "Aktuell sind keine spezifischen Stellen ausgeschrieben. Wir freuen uns jedoch jederzeit über Initiativbewerbungen."
}
